octoconf/__init__.py
octoconf/octoconf.py
octoconf-0.2.2.dist-info/METADATA
octoconf-0.2.2.dist-info/RECORD
octoconf-0.2.2.dist-info/WHEEL
octoconf-0.2.2.dist-info/top_level.txt
