Metadata-Version: 2.1
Name: octoconf
Version: 0.2.2
Summary: Multi-profile supported, flexible config library
Home-page: https://github.com/andras-tim/octoconf
Author: Andras Tim
Author-email: andras.tim@gmail.com
License: GPLv3
Keywords: yaml config multi-profile inheritance
Platform: any
Classifier: Development Status :: 5 - Production/Stable
Classifier: Intended Audience :: Developers
Classifier: License :: OSI Approved :: GNU General Public License v3 (GPLv3)
Classifier: Programming Language :: Python :: 2
Classifier: Programming Language :: Python :: 3
Requires-Dist: PyYAML (<4.0,>=3.11)
